stelios/analytics/__init__.py
stelios/analytics/client.py
stelios/analytics/consumer.py
stelios/analytics/oauth_manager.py
stelios/analytics/request.py
stelios/analytics/utils.py
stelios/analytics/version.py
stelios/analytics/test/__init__.py
stelios/analytics/test/client.py
stelios/analytics/test/consumer.py
stelios/analytics/test/module.py
stelios/analytics/test/oauth.py
stelios/analytics/test/request.py
stelios/analytics/test/utils.py
stelios_analytics_python_test-2.2.3.dist-info/LICENSE
stelios_analytics_python_test-2.2.3.dist-info/METADATA
stelios_analytics_python_test-2.2.3.dist-info/WHEEL
stelios_analytics_python_test-2.2.3.dist-info/top_level.txt
stelios_analytics_python_test-2.2.3.dist-info/RECORD
